{
  "safetyTips": "Fully insured, we wear gloves and face mask, delivery by drop off at door.",
  "name": "CALIFORNIA CRAVINGS",
  "phone": "07458301159",
  "address": "Faversham, Kent, ME13 7ER",
  "cover": "https://res.cloudinary.com/dhult2ubt/image/upload/c_limit,f_auto,q_80,w_500/v1589283391/Screen_Shot_2020-05-12_at_12.36.06_PM_n9b9sm.png",
  "tags": [
    "Food",
    "Alcohol",
    "Beer",
    "Wine"
  ],
  "website": "https://www.californiacravings.com/",
  "deliveryHours": [
    "Thursday 12:00 - 15:00"
  ],
  "email": "christina@californiacravings.com",
  "description": "We offer Mexican-American themed ready-meals for delivery. We also carry fine wine, beer and margaritas to give our customers the restaurant experience in the comfort of their own home. Order on website."
}