{
  "safetyTips": "We are Covid compliant.",
  "name": "ROSEWOOD COUNTRY STYLE",
  "phone": "07773754299",
  "address": "Sellindge, Ashford, Kent.",
  "cover": "https://res.cloudinary.com/dhult2ubt/image/upload/c_limit,f_auto,q_80,w_500/v1593419670/41D05646-53A9-4A08-98D8-E6EA84D5C83A_uojojs.jpg",
  "tags": [
    "Gifts",
    "Clothing",
    "Accessories"
  ],
  "website": "http://www.rosewoodcountrystyle.co.uk",
  "deliveryHours": [
    "Monday 10:00 - 17:00",
    "Tuesday 10:00 - 17:00",
    "Wednesday 10:00 - 17:00",
    "Thursday 10:00 - 17:00",
    "Friday 10:00 - 17:00"
  ],
  "email": "info@rosewoodcountrystyle.co.uk",
  "description": "We are family run business selling all shooting, tweed, and country style accessories. Order via Website or Facebook. "
}